azure_openai/__init__.py
azure_openai/chat_completion.py
microsoft_openai-0.1.0.dist-info/LICENSE
microsoft_openai-0.1.0.dist-info/METADATA
microsoft_openai-0.1.0.dist-info/WHEEL
microsoft_openai-0.1.0.dist-info/top_level.txt
microsoft_openai-0.1.0.dist-info/RECORD
